
<annotation>
    <folder>images</folder>
    <filename>BikesHelmets719.png</filename>
    <size>
        <width>494</width>
        <height>467</height>
        <depth>3</depth>
    </size>
    <segmented>0</segmented>
    <object>
        <name>With Helmet</name>
        <pose>Unspecified</pose>
        <truncated>0</truncated>
        <occluded>0</occluded>
        <difficult>0</difficult>
        <bndbox>
            <xmin>262</xmin>
            <ymin>85</ymin>
            <xmax>314</xmax>
            <ymax>143</ymax>
        </bndbox>
    </object>
</annotation>